openai_batch_api/OpenaiBatchAPI.py
openai_batch_api/__init__.py
openai_batch_api/model/__init__.py
openai_batch_api/model/batch.py
openai_batch_api/model/file.py
openai_batch_api/utils/__init__.py
openai_batch_api/utils/prices.py
OpenaiBatchAPI-1.1.1.dist-info/METADATA
OpenaiBatchAPI-1.1.1.dist-info/WHEEL
OpenaiBatchAPI-1.1.1.dist-info/top_level.txt
OpenaiBatchAPI-1.1.1.dist-info/RECORD
