Metadata-Version: 2.1
Name: OpenaiBatchAPI
Version: 1.1.1
Summary: OpenaiBatchAPI: A Python Library that supports OpenAI Batch API
Home-page: https://github.com/it-dainb/batch_api.git
Author: IT.DAINB
Author-email: it.dainb@gmail.com
License: Apache License 2.0
Keywords: openai batch_api batch api
Classifier: Programming Language :: Python :: 3.8
Classifier: Programming Language :: Python :: 3.9
Classifier: Programming Language :: Python :: 3.10
Classifier: Programming Language :: Python :: 3.11
Classifier: Programming Language :: Python :: 3.12
Requires-Python: >=3.8, <=3.12
Requires-Dist: uuid
Requires-Dist: orjsonl
Requires-Dist: openai
Requires-Dist: tqdm
Requires-Dist: prettytable
